<?xml version="1.0" encoding="UTF-8"?>
<amendments>
   <header>
      <billtitle>Care_(HLBill1_III(k))</billtitle>
      <headertext>AMENDMENTS TO BE MOVED IN COMMITTEE</headertext>
      <headertext>[Supplementary to the Third Marshalled List]</headertext>
   </header>
   <clausenumber>Clause 80</clausenumber>
   <proposer>BARONESS GREENGROSS</proposer>
   <Amendment>
      <Number>000</Number>
      <text>
         <quote>
            <B>000:</B> Clause 80, page 68, line 7, at end insert&#8212;</quote>
         <IndentOne>&#8220;(c) describing the manner in which it expects a registered service providers or local authority to handle complaints and concerns&#8221;</IndentOne>
      </text>
   </Amendment>
   <Amendment>
      <Number>000</Number>
      <text>
         <quote>
            <B>000:</B> Clause 80, page 68, line 15, at end insert&#8212;</quote>
         <quote>&#8220;( ) Indicators the Commission devises for the purposes of subsection (5) may in particular include indicators of the quality of services provided for the identification and treatment of incontinence.&#8221;</quote>
      </text>
   </Amendment>
   <clausenumber>Clause 1</clausenumber>
   <proposer>BARONESS GREENGROSS</proposer>
   <Amendment>
      <Number>000</Number>
      <text>
         <quote>
            <B>000:</B> Clause 1, page 2, line 7, after &#8220;support&#8221; insert &#8220;or need for health provision and the importance of reducing needs of either kind that already exist,&#8221;</quote>
      </text>
   </Amendment>
   <clausenumber>Clause 2</clausenumber>
   <proposer>BARONESS GREENGROSS</proposer>
   <Amendment>
      <Number>000</Number>
      <text>
         <quote>
            <B>000:</B> Clause 2, page 2, line 36, at end insert &#8220;and health provision&#8221;</quote>
      </text>
   </Amendment>
   <Amendment>
      <Number>000</Number>
      <text>
         <quote>
            <B>000:</B> Clause 2, page 2, line 39, after &#8220;support&#8221; insert &#8220;and health provision&#8221;</quote>
      </text>
   </Amendment>
   <Amendment>
      <Number>000</Number>
      <text>
         <quote>
            <B>000:</B> Clause 2, page 2, line 40, at end insert&#8212;</quote>
         <IndentOne>&#8220;(e) otherwise prevent or delay deterioration in the well-being of adults in its area&#8221;</IndentOne>
      </text>
   </Amendment>
   <Amendment>
      <Number>000</Number>
      <text>
         <quote>
            <B>000:</B> Clause 2, page 3, line 2, at end insert&#8212;</quote>
         <IndentOne>&#8220;(d) the steps it could take to improve and enhance the provision of services, facilities or resources in its area&#8221;</IndentOne>
      </text>
   </Amendment>
   <Amendment>
      <Number>000</Number>
      <text>
         <quote>
            <B>000:</B> Clause 2, page 3, line 2, at end insert&#8212;</quote>
         <IndentOne>&#8220;(e) clinical guidelines and quality standards produced by the National Institute for Health and Clinical Excellence&#8221;</IndentOne>
      </text>
   </Amendment>
   <clausenumber>Clause 4</clausenumber>
   <proposer>BARONESS MEACHER</proposer>
   <proposer>BARONESS GREENGROSS</proposer>
   <Amendment>
      <Number>000</Number>
      <text>
         <quote>
            <B>000:</B> Clause 4, page 4, line 9, leave out &#8220;and maintain&#8221; and insert &#8220;, maintain and facilitate access to&#8221;</quote>
      </text>
   </Amendment>
   <proposer>BARONESS GREENGROSS</proposer>
   <Amendment>
      <Number>000</Number>
      <text>
         <quote>
            <B>000:</B> Clause 4, page 4, line 23, at end insert&#8212;</quote>
         <quote>&#8220;( ) The local authority must produce, or arrange for the production of, packs of information relevant to the needs of individuals with specific medical conditions and ensure these packs are provided to individuals following the diagnosis of a specific condition.&#8221;</quote>
      </text>
   </Amendment>
   <proposer>BARONESS MEACHER</proposer>
   <Amendment>
      <Number>000</Number>
      <text>
         <quote>
            <B>000:</B> Clause 4, page 4, line 24, at end insert&#8212;</quote>
         <quote>&#8220;( ) The local authority must produce, or arrange for the production of, packs of information relevant to the needs of individuals with specific medical conditions and ensure these packs are provided to individuals following the diagnosis of a specific condition.&#8221;</quote>
      </text>
   </Amendment>
   <proposer>BARONESS BROWNING</proposer>
   <Amendment>
      <Number>000</Number>
      <text>
         <quote>
            <B>000:</B> Clause 4, page 4, line 38, at end insert&#8212;</quote>
         <quote>&#8220;(6) Regulations must make further provision in relation to information and advice; and in particular in order to ensure that information and advice are proportionate to the needs of those for whom it is provided, a local authority must require social work-qualified staff to provide information and advice in cases where present or foreseeable needs are classified as complex.&#8221;</quote>
      </text>
   </Amendment>
   <clausenumber>Clause 5</clausenumber>
   <proposer>BARONESS GREENGROSS</proposer>
   <Amendment>
      <Number>000</Number>
      <text>
         <quote>
            <B>000:</B> Clause 5, page 5, line 19, at end insert&#8212;</quote>
         <IndentOne>&#8220;(f) the importance of ensuring that the tariff price rates for care provision reflect the actual cost of care&#8221;</IndentOne>
      </text>
   </Amendment>
   <Amendment>
      <Number>000</Number>
      <text>
         <quote>
            <B>000:</B> Clause 5, page 5, line 19, at end insert&#8212;</quote>
         <IndentOne>&#8220;(g) the need to appoint an independent adjudicator to settle disputes between the local authority and care providers over the tariff price rate of care&#8221;</IndentOne>
      </text>
   </Amendment>
   <Amendment>
      <Number>000</Number>
      <text>
         <quote>
            <B>000:</B> Clause 5, page 5, line 19, at end insert&#8212;</quote>
         <IndentOne>&#8220;( ) the need to adhere to specific minimum quality standards and requirements in the commissioning and provision of services to adults, as regulations may prescribe&#8221;</IndentOne>
      </text>
   </Amendment>
   <Amendment>
      <Number>000</Number>
      <text>
         <quote>
            <B>000:</B> Clause 5, page 5, line 19, at end insert&#8212;</quote>
         <quote>&#8220;( ) Regulations made under this section may not normally specify that visits to deliver personal care in an adult&#8217;s home last a specified time shorter than the time taken to deliver the care required.&#8221;</quote>
      </text>
   </Amendment>
   <clausenumber>Clause 9</clausenumber>
   <proposer>BARONESS GREENGROSS</proposer>
   <Amendment>
      <Number>000</Number>
      <text>
         <quote>
            <B>000:</B> Clause 9, page 8, line 9, at end insert&#8212;</quote>
         <quote>&#8220;if the needs can be prevented from getting worse and how the needs may be reduced&#8221;</quote>
      </text>
   </Amendment>
   <clausenumber>Clause 10</clausenumber>
   <proposer>BARONESS PITKEATHLEY</proposer>
   <Amendment>
      <Number>000</Number>
      <text>
         <quote>
            <B>000:</B> Clause 10, page 9, line 37, at end insert&#8212;</quote>
         <quote>&#8220;(11) Where an adult is being assessed for NHS Continuing Care and this is to be provided in whole or in part in the community, and that person has a carer who is providing or about to provide care, the local authority must ensure that a carer&#8217;s assessment under this section and section 12 is carried out of the carer&#8217;s ability to provide or continue to provide care.&#8221;</quote>
      </text>
   </Amendment>
   <clausenumber>After Clause 10</clausenumber>
   <proposer>BARONESS BROWNING</proposer>
   <Amendment>
      <Number>000</Number>
      <text>
         <quote>
            <B>000:</B> After Clause 10, insert the following new Clause&#8212;</quote>
         <quote>&#8220;Duty to provide independent advocacy</quote>
         <quote>(1) A local authority has a duty to provide an independent advocate to assist any qualifying adult under this Act for the purposes of assessment, supporting planning or review processes or both.</quote>
         <quote>(2) An adult is a qualifying adult if&#8212;</quote>
         <IndentOne>(a) the adult&#8217;s needs for care and support are being assessed under section 9 or a care and support plan is being prepared for the adult under section 25 or a review of the adult&#8217;s needs is conducted under section 27, and</IndentOne>
         <IndentOne>(b) the local authority considers that without the assistance of an advocate the adult will experience substantial difficulty in relation to one or more of the following&#8212;</IndentOne>
         <IndentTwo>(i) understanding, retaining, using or weighing the information relevant to the process of assessment, care and support planning or review,</IndentTwo>
         <IndentTwo>(ii) expressing or communicating their own views or wishes and feelings, or</IndentTwo>
         <IndentOne>(c) the adult is an individual to whom section 11(2)(a) or (b) of this Act applies, or</IndentOne>
         <IndentOne>(d) the adult is a carer for whom the local authority is undertaking a carers assessment in accordance with section 10(1) and the local authority considers that without the assistance of an advocate the carer will experience substantial difficulty in relation to one or more of the following&#8212;</IndentOne>
         <IndentTwo>(i) understanding, retaining, using or weighing the information relevant to the process of assessment, support planning or review,</IndentTwo>
         <IndentTwo>(ii) expressing or communicating their own views or wishes and feelings.</IndentTwo>
         <quote>(3) Regulations may be made as to&#8212;</quote>
         <IndentOne>(a) the appointment of advocates,</IndentOne>
         <IndentOne>(b) the skills or qualifications of advocates,</IndentOne>
         <IndentOne>(c) the duties of advocates,</IndentOne>
         <IndentOne>(d) the right of access for advocates to the adult,</IndentOne>
         <IndentOne>(e) the duty to take account of representations by the advocate on behalf of the adult,</IndentOne>
         <IndentOne>(f) the right of access for advocates to the adult&#8217;s relevant personal data including records held by local authorities and health authorities, and</IndentOne>
         <IndentOne>(g) additional circumstances in which an advocate must be provided.&#8221;</IndentOne>
      </text>
   </Amendment>
   <clausenumber>Clause 12</clausenumber>
   <proposer>BARONESS BROWNING</proposer>
   <Amendment>
      <Number>000</Number>
      <text>
         <quote>
            <B>000:</B> Clause 12, page 10, line 43, at end insert&#8212;</quote>
         <IndentOne>&#8220;(h) specify circumstances in which a person&#8217;s social care needs are to be regarded as complex and stipulate that social work-qualified staff should always be used in the assessment of complex needs as defined.&#8221;</IndentOne>
      </text>
   </Amendment>
   <clausenumber>Clause 14</clausenumber>
   <proposer>BARONESS PITKEATHLEY</proposer>
   <Amendment>
      <Number>000</Number>
      <text>
         <quote>
            <B>000:</B> Clause 14, page 13, line 7, at end insert&#8212;</quote>
         <quote>&#8220;(8) Where an assessment is carried out under subsection 10, the NHS must meet the carer&#8217;s assessed needs for support which meet the eligibility criteria free of charge.&#8221;</quote>
      </text>
   </Amendment>
   <clausenumber>Clause 25</clausenumber>
   <proposer>LORD DUBS</proposer>
   <Amendment>
      <Number>000</Number>
      <text>
         <quote>
            <B>000:</B> Clause 25, page 21, line 19, at end insert&#8212;</quote>
         <IndentOne>&#8220;(g) specifies what should happen in the event of an emergency or if needs change&#8221;</IndentOne>
      </text>
   </Amendment>
   <Amendment>
      <Number>000</Number>
      <text>
         <quote>
            <B>000:</B> Clause 25, page 21, line 19, at end insert&#8212;</quote>
         <IndentOne>&#8220;(h) specifies an anticipated review date, agreed between&#8212;</IndentOne>
         <IndentTwo>(i) the adult for whom it is being prepared;</IndentTwo>
         <IndentTwo>(ii) any carer that the adult has; and</IndentTwo>
         <IndentTwo>(iii) any person whom the adult asks the authority to involve or, where the adult lacks capacity to ask the authority to do&#8221;</IndentTwo>
      </text>
   </Amendment>
   <clausenumber>Clause 28</clausenumber>
   <proposer>BARONESS GREENGROSS</proposer>
   <Amendment>
      <Number>000</Number>
      <text>
         <quote>
            <B>000:</B> Clause 28, page 24, line 26, at end insert&#8212;</quote>
         <quote>&#8220;(8) But the local authority may not rely on subsection (7) (and so must carry out a needs assessment) if the adult lacks capacity to refuse the assessment and the authority is satisfied that carrying out the assessment would be in the adult&#8217;s best interests.&#8221;</quote>
      </text>
   </Amendment>
   <clausenumber>Clause 69</clausenumber>
   <proposer>EARL HOWE</proposer>
   <Amendment>
      <Number>000</Number>
      <text>
         <quote>
            <B>000:</B> Clause 69, page 57, line 7, at end insert&#8212;</quote>
         <quote>&#8220;( ) In its application to an adult who is residing in any other premises because a requirement to do so has been imposed on the adult as a condition of the grant of bail in criminal proceedings, this Part has effect as if references to being ordinarily resident in an area were references to being resident in premises in that area for that reason.&#8221;</quote>
      </text>
   </Amendment>
   <Amendment>
      <Number>000</Number>
      <text>
         <quote>
            <B>000:</B> Clause 69, page 57, line 28, at end insert&#8212;</quote>
         <quote>&#8220;(6A) An SAB&#8217;s objective under section 42(2) does not include helping and protecting adults who are detained in prison or residing in approved premises; but an SAB may nonetheless provide advice or assistance to any person for the purpose of helping and protecting such adults in its area in cases of the kind described in section 41(1) (adults with needs for care and support who are at risk of abuse or neglect).&#8221;</quote>
      </text>
   </Amendment>
   <Amendment>
      <Number>000</Number>
      <text>
         <quote>
            <B>000:</B> Clause 69, page 57, line 28, at end insert&#8212;</quote>
         <quote>&#8220;(6B) Section 43 (safeguarding adults reviews) does not apply to any case involving an adult in so far as the case relates to any period during which the adult was&#8212;</quote>
         <IndentOne>(a) detained in prison, or</IndentOne>
         <IndentOne>(b) residing in approved premises.&#8221;</IndentOne>
      </text>
   </Amendment>
   <Amendment>
      <Number>000</Number>
      <text>
         <quote>
            <B>000:</B> Clause 69, page 57, line 31, leave out from second &#8220;officer&#8221; to end of line 34</quote>
      </text>
   </Amendment>
   <Amendment>
      <Number>000</Number>
      <text>
         <quote>
            <B>000:</B> Clause 69, page 57, line 39, leave out &#8220;references&#8221; and insert &#8220;reference&#8221;</quote>
      </text>
   </Amendment>
   <Amendment>
      <Number>000</Number>
      <text>
         <quote>
            <B>000:</B> Clause 69, page 57, line 40, leave out &#8220;include&#8221; and insert &#8220;includes&#8221;</quote>
      </text>
   </Amendment>
   <Amendment>
      <Number>000</Number>
      <text>
         <quote>
            <B>000:</B> Clause 69, page 57, line 44, leave out &#8220;references&#8221; and insert &#8220;reference&#8221;</quote>
      </text>
   </Amendment>
   <Amendment>
      <Number>000</Number>
      <text>
         <quote>
            <B>000:</B> Clause 69, page 57, line 45, leave out &#8220;include&#8221; and insert &#8220;includes&#8221;</quote>
      </text>
   </Amendment>
   <Amendment>
      <Number>000</Number>
      <text>
         <quote>
            <B>000:</B> Clause 69, page 58, line 2, at end insert&#8212;</quote>
         <quote>&#8220;( ) &#8220;Bail in criminal proceedings&#8221; has the meaning given in section 1 of the Bail Act 1976.&#8221;</quote>
      </text>
   </Amendment>
   <Amendment>
      <Number>000</Number>
      <text>
         <quote>
            <B>000:</B> Clause 69, page 58, line 4, leave out paragraphs (a) and (b)</quote>
      </text>
   </Amendment>
   <Amendment>
      <Number>000</Number>
      <text>
         <quote>
            <B>000:</B> Clause 69, page 58, line 11, after first &#8220;is&#8221; insert &#8220;temporarily&#8221;</quote>
      </text>
   </Amendment>
   <Amendment>
      <Number>000</Number>
      <text>
         <quote>
            <B>000:</B> Clause 69, page 58, line 13, after first &#8220;is&#8221; insert &#8220;temporarily&#8221;</quote>
      </text>
   </Amendment>
   <Amendment>
      <Number>000</Number>
      <text>
         <quote>
            <B>000:</B> Clause 69, page 58, line 14, at end insert&#8212;</quote>
         <IndentOne>&#8220;( ) a person who is temporarily absent from other premises in which the person is required to reside as a condition of the grant of bail in criminal proceedings is to be treated as residing in the premises for the period of absence&#8221;</IndentOne>
      </text>
   </Amendment>
</amendments>