<?xml version="1.0" encoding="UTF-8"?><Legislation SchemaVersion="1.0" xsi:schemaLocation="http://www.tso.co.uk/assets/namespace/legislation C:\development\projects\ActsToSchema\legislationSchema\schema\schemaLegislationBase-v1-0.xsd" xmlns="http://www.tso.co.uk/assets/namespace/legislation" xmlns:xsi="http://www.w3.org/2001/XMLSchema-instance" xmlns:xhtml="http://www.w3.org/1999/xhtml" xmlns:leg="http://www.tso.co.uk/assets/namespace/legislation" xmlns:dc="http://purl.org/dc/elements/1.1/" xmlns:ukm="http://www.tso.co.uk/assets/namespace/metadata" xmlns:fo="http://www.w3.org/1999/XSL/Format">
<ukm:Metadata>
<dc:title>Commercial Lobbyists (Registration and Code of Conduct) Bill</dc:title>
<dc:identifier>ISBN TO GO HERE</dc:identifier>
<dc:language>en</dc:language>
<dc:creator>Parliamentary Counsel</dc:creator>
<dc:date>31/1/2013</dc:date>
<ukm:BillMetadata>
<ukm:DocumentClassification>
<ukm:DocumentCategory Value="Bill" />
<ukm:DocumentMainType Value="PublicBill" />
<ukm:DocumentStatus Value="final" />
</ukm:DocumentClassification>
<ukm:Number Value="Bill 39" />
<ukm:Parliament Value="55" />
<ukm:Session Value="2" />
<ukm:House Value="House of Commons" />
</ukm:BillMetadata>
</ukm:Metadata>
<Contents>
<Rubric TemplateVersion="4.2.002" xmlns="" /><Rubric xmlns="" /><ContentsTitle>Contents</ContentsTitle>
<ContentsItem ContentRef="p00007">
<ContentsNumber>1</ContentsNumber>
<ContentsTitle>Registration of lobbyists</ContentsTitle>
</ContentsItem>
<ContentsItem ContentRef="p00008">
<ContentsNumber>2</ContentsNumber>
<ContentsTitle>Offence of non-registration</ContentsTitle>
</ContentsItem>
<ContentsItem ContentRef="p00009">
<ContentsNumber>3</ContentsNumber>
<ContentsTitle>Code of conduct</ContentsTitle>
</ContentsItem>
<ContentsItem ContentRef="p00010">
<ContentsNumber>4</ContentsNumber>
<ContentsTitle>Definition of lobbying</ContentsTitle>
</ContentsItem>
<ContentsItem ContentRef="p00011">
<ContentsNumber>5</ContentsNumber>
<ContentsTitle>Orders and regulations</ContentsTitle>
</ContentsItem>
<ContentsItem ContentRef="p00012">
<ContentsNumber>6</ContentsNumber>
<ContentsTitle>Short title, commencement and extent</ContentsTitle>
</ContentsItem>
</Contents>
<Primary>
<PrimaryPrelims>
<Title><?start-line?>A
<?new-line?>Bill

<?new-line?>To
</Title>
<Number /><LongTitle><?start-line?><Para>
<Text>Establish a public register of organisations and individuals that carry out <?new-line?>lobbying of Parliament, the Government and local authorities for financial <?new-line?>gain; to introduce a code of conduct for those on the register; to introduce <?new-line?>sanctions for non-registration and non-compliance with the code of conduct; <?new-line?>and for connected purposes.<DateOfEnactment><DateText /></DateOfEnactment>
</Text>
</Para>
</LongTitle>
<DateOfEnactment><DateText /></DateOfEnactment>
<PrimaryPreamble>
<EnactingText>
<Para>
<Text>B<SmallCaps>e it enacted</SmallCaps> by the Queen’s most Excellent Majesty, by and with the advice and <?new-line?>consent of the Lords Spiritual and Temporal, and Commons, in this present <?new-line?>Parliament assembled, and by the authority of the same, as follows:—</Text>
</Para>
</EnactingText>
</PrimaryPreamble>
</PrimaryPrelims>
<Body NumberFormat="default">
<P1group id="p00007">
<Title><?start-line?>Registration of lobbyists</Title>
<P1>
<Pnumber>1</Pnumber>
<P1para>
<P2>
<Pnumber>1</Pnumber>
<P2para>
<Text><?start-line?>There shall be a register of organisations and individuals who carry out <?new-line?>lobbying of Parliament, the Government and local authorities for financial <?new-line?>gain, which shall be made public.</Text>
</P2para>
</P2>
<P2>
<Pnumber>2</Pnumber>
<P2para>
<Text><?start-line?>There shall be a Lobbying Registration Council to supervise the register and <?new-line?>keep it up to date.</Text>
</P2para>
</P2>
<P2>
<Pnumber>3</Pnumber>
<P2para>
<Text><?start-line?><Emphasis>The Council shall be funded by fees charged to those organisations and individuals who <?new-line?>register.</Emphasis></Text>
</P2para>
</P2>
<P2>
<Pnumber>4</Pnumber>
<P2para>
<Text><?start-line?>The Secretary of State may by regulations provide for the appointment of the <?new-line?>Council and its proceedings, the particulars to be entered on the register, and <?new-line?>the fees to be charged, which shall be calculated to cover the costs of the <?new-line?>Council.</Text>
</P2para>
</P2>
<P2>
<Pnumber>5</Pnumber>
<P2para>
<Text><?start-line?>Those organisations and individuals which are included on the register shall, <?new-line?>at intervals of no more than three months, provide details for the register of the <?new-line?>names of clients for whom they have lobbied.</Text>
</P2para>
</P2>
</P1para>
</P1>
</P1group>
<P1group id="p00008">
<Title><?start-line?>Offence of non-registration</Title>
<P1>
<Pnumber>2</Pnumber>
<P1para>
<Text><?start-line?>An organisation which or individual who lobbies Parliament, the Government <?new-line?>or a local authority for financial gain without being registered shall be liable on <?new-line?>summary conviction to a fine not exceeding level 5 on the standard scale.</Text>
</P1para>
</P1>
</P1group>
<?new-page?><P1group id="p00009">
<Title><?start-line?>Code of conduct</Title>
<P1>
<Pnumber>3</Pnumber>
<P1para>
<P2>
<Pnumber>1</Pnumber>
<P2para>
<Text><?start-line?>The Council shall prepare a code of conduct with which those included on the <?new-line?>register shall comply, and may produce revised codes from time to time.</Text>
</P2para>
</P2>
<P2>
<Pnumber>2</Pnumber>
<P2para>
<Text><?start-line?>The Secretary of State shall give statutory effect to the code and any revised <?new-line?>code by order.</Text>
</P2para>
</P2>
<P2>
<Pnumber>3</Pnumber>
<P2para>
<Text><?start-line?>Any code shall provide that nobody may act undertake lobbying who holds a <?new-line?>pass conferring access to the Houses of Parliament other than as a spouse or <?new-line?>civil partner of a member or former member of either House of Parliament.</Text>
</P2para>
</P2>
<P2>
<Pnumber>4</Pnumber>
<P2para>
<Text><?start-line?>An organisation or person included on the register which contravenes the <?new-line?>provisions of the code of conduct shall be liable on summary conviction to a <?new-line?>fine not exceeding level 4 on the standard scale.</Text>
</P2para>
</P2>
</P1para>
</P1>
</P1group>
<P1group id="p00010">
<Title><?start-line?>Definition of lobbying</Title>
<P1>
<Pnumber>4</Pnumber>
<P1para>
<P2>
<Pnumber>1</Pnumber>
<P2para>
<Text><?start-line?>For the purpose of this Act “lobbying” means any activity carried out in the <?new-line?>course of a business or employment which are undertaken for financial gain <?new-line?>and are designed to influence the Government of the United Kingdom, <?new-line?>Parliament, any local authority in England or any member or employee of any <?new-line?>of those bodies in formulating its official policy.</Text>
</P2para>
</P2>
<P2>
<Pnumber>2</Pnumber>
<P2para>
<Text><?start-line?>“Lobbying” does not include activities undertaken in the course of their duties <?new-line?>by Members of either House of the United Kingdom Parliament or of any local <?new-line?>authority in England.</Text>
</P2para>
</P2>
</P1para>
</P1>
</P1group>
<P1group id="p00011">
<Title><?start-line?>Orders and regulations</Title>
<P1>
<Pnumber>5</Pnumber>
<P1para>
<Text><?start-line?>Orders and regulations under this Act shall be made by statutory instrument <?new-line?>and may not be made unless a draft of the instrument has been laid before, and <?new-line?>approved by resolution of, each House of Parliament.</Text>
</P1para>
</P1>
</P1group>
<P1group id="p00012">
<Title><?start-line?>Short title, commencement and extent</Title>
<P1>
<Pnumber>6</Pnumber>
<P1para>
<P2>
<Pnumber>1</Pnumber>
<P2para>
<Text><?start-line?>This Act may be cited as the Commercial Lobbyists (Registration and Code of <?new-line?>Conduct) Act 2013.</Text>
</P2para>
</P2>
<P2>
<Pnumber>2</Pnumber>
<P2para>
<Text><?start-line?>This Act shall come into force at the expiration of the period of six months <?new-line?>beginning on the day on which it is passed.</Text>
</P2para>
</P2>
<P2>
<Pnumber>3</Pnumber>
<P2para>
<Text><?start-line?>This Act shall extend to England and Wales, Scotland and Northern Ireland.</Text>
</P2para>
</P2>
</P1para>
</P1>
</P1group>
</Body>
</Primary>
</Legislation>